README.md
setup.cfg
setup.py
wwpdb/__init__.py
wwpdb.apps.releasemodule.egg-info/PKG-INFO
wwpdb.apps.releasemodule.egg-info/SOURCES.txt
wwpdb.apps.releasemodule.egg-info/dependency_links.txt
wwpdb.apps.releasemodule.egg-info/not-zip-safe
wwpdb.apps.releasemodule.egg-info/requires.txt
wwpdb.apps.releasemodule.egg-info/top_level.txt
wwpdb/apps/__init__.py
wwpdb/apps/releasemodule/__init__.py
wwpdb/apps/releasemodule/citation/Analysis.py
wwpdb/apps/releasemodule/citation/CheckResult.py
wwpdb/apps/releasemodule/citation/CitationFinder.py
wwpdb/apps/releasemodule/citation/FetchMP.py
wwpdb/apps/releasemodule/citation/FetchResultParser.py
wwpdb/apps/releasemodule/citation/FetchUtil.py
wwpdb/apps/releasemodule/citation/MatchMP.py
wwpdb/apps/releasemodule/citation/MatchUtil.py
wwpdb/apps/releasemodule/citation/MonitorCitationUpdate.py
wwpdb/apps/releasemodule/citation/ReadCitationFinderResult_v2.py
wwpdb/apps/releasemodule/citation/RisCitationParser.py
wwpdb/apps/releasemodule/citation/SearchMP.py
wwpdb/apps/releasemodule/citation/SearchResultParser.py
wwpdb/apps/releasemodule/citation/SearchUtil.py
wwpdb/apps/releasemodule/citation/StringUtil.py
wwpdb/apps/releasemodule/citation/__init__.py
wwpdb/apps/releasemodule/depict/DepictAnnotatorHistory.py
wwpdb/apps/releasemodule/depict/DepictBase.py
wwpdb/apps/releasemodule/depict/DepictCitationForm_v2.py
wwpdb/apps/releasemodule/depict/DepictCitation_v2.py
wwpdb/apps/releasemodule/depict/DepictEntryHistory.py
wwpdb/apps/releasemodule/depict/DepictReleaseInfo.py
wwpdb/apps/releasemodule/depict/DepictRemovalMark.py
wwpdb/apps/releasemodule/depict/DepictRequest.py
wwpdb/apps/releasemodule/depict/ReleaseOption_v2.py
wwpdb/apps/releasemodule/depict/__init__.py
wwpdb/apps/releasemodule/depict/test_DepictCitation.py
wwpdb/apps/releasemodule/update/AutoReRelease.py
wwpdb/apps/releasemodule/update/CitationFormParser_v2.py
wwpdb/apps/releasemodule/update/EmReleaseUtil.py
wwpdb/apps/releasemodule/update/EntryFormParser_v2.py
wwpdb/apps/releasemodule/update/EntryPullProcess.py
wwpdb/apps/releasemodule/update/EntryUpdateBase.py
wwpdb/apps/releasemodule/update/EntryUpdateProcess.py
wwpdb/apps/releasemodule/update/InputFormParser_v2.py
wwpdb/apps/releasemodule/update/MultiUpdateProcess.py
