Metadata-Version: 2.4
Name: wwpdb.apps.releasemodule
Version: 0.32.6
Summary: wwPDB sequence module
Home-page: https://github.com/rcsb/py-wwpdb_apps_releasemodule
Author: Ezra Peisach
Author-email: ezra.peisach@rcsb.org
License: Apache 2.0
Classifier: Development Status :: 3 - Alpha
Classifier: Intended Audience :: Developers
Classifier: Natural Language :: English
Classifier: License :: OSI Approved :: Apache Software License
Classifier: Programming Language :: Python
Classifier: Programming Language :: Python :: 2.7
Classifier: Programming Language :: Python :: 3
Classifier: Programming Language :: Python :: 3.6
Classifier: Programming Language :: Python :: 3.7
Requires-Dist: mmcif
Requires-Dist: wwpdb.apps.msgmodule
Requires-Dist: wwpdb.apps.wf_engine
Requires-Dist: wwpdb.io
Requires-Dist: wwpdb.utils.config>=0.24
Requires-Dist: wwpdb.utils.dp~=0.48
Requires-Dist: wwpdb.utils.emdb~=1.0
Requires-Dist: wwpdb.utils.session
Requires-Dist: wwpdb.utils.wf
Requires-Dist: mmcif.utils
Requires-Dist: wwpdb.utils.db>=0.8
Requires-Dist: rcsb.utils.multiproc
Provides-Extra: dev
Requires-Dist: check-manifest; extra == "dev"
Provides-Extra: test
Requires-Dist: coverage; extra == "test"
Dynamic: author
Dynamic: author-email
Dynamic: classifier
Dynamic: description
Dynamic: home-page
Dynamic: license
Dynamic: provides-extra
Dynamic: requires-dist
Dynamic: summary
